{"pagina-pre_registro":{"str-titulo-card-1":"APOIADOR","str-titulo-card-2":"CAPTADOR","str-titulo-card-3":"REALIZADOR","str-desc-card-1":"O portal do apoiador \u00e9 onde voc\u00ea poder\u00e1 encontrar projetos para serem apoiados.","str-desc-card-2":"O portal do captador \u00e9 onde voc\u00ea poder\u00e1 encontrar clientes para realizar a capta\u00e7\u00e3o de recursos.","str-desc-card-3":"O portal do realizador \u00e9 onde voc\u00ea poder\u00e1 cadastrar seus novos projetos.","str-titulo-pagina":"Projecta :: Acesso","str-titulo-cards":"Registre-se em um de nossos portais:","str-btn_acesso":"REGISTRE-SE","desc-card-1":"asfasfasf"},"pagina-cadastro":{"str-titulo-card":"Abrir conta Trial","str-desc-card":"Campos marcados com <span class=\"text-danger\"><b>*<\/b><\/span> s\u00e3o obrigat\u00f3rios.","str-label-inputNome":"Nome completo <span class=\"text-danger\"><b>*<\/b><\/span>","str-label-inputEmail":"Endere\u00e7o de Email <span class=\"text-danger\"><b>*<\/b><\/span>","str-label-inputEmpresa":"Empresa","str-label-inputCargo":"Seu cargo na empresa","str-label-inputTelefone":"Telefone <span class=\"text-danger\"><b>*<\/b><\/span>","str-label-inputProposito":"Selecione seu prop\u00f3sito ao usar o Projecta <span class=\"text-danger\"><b>*<\/b><\/span>","str-label-inputPorte":"Selecione o porte de sua empresa <span class=\"text-danger\"><b>*<\/b><\/span>","str-label-inputSenha":"Senha <span class=\"text-danger\"><b>*<\/b><\/span>","str-label-inputConfirmarSenha":"Confirme sua senha <span class=\"text-danger\"><b>*<\/b><\/span>","str-label-inputTermos":"Aceito os <a href=\"#\">termos<\/a>","str-titulo-pagina":"Projecta :: Cadastro","str-texto-btn-registrar":"REGISTRAR","options-select-inputProposito":["Realizar projetos","Apoiar projetos financeiramente","Captar recursos"],"options-select-inputPorte":["Grande empresa","M\u00e9dia empresa","Pequena empresa","Micro empresa","Empresa individual","Pessoa f\u00edsica"]},"pagina-esqueceu_senha":{"str-titulo-card":"Recupera\u00e7\u00e3o de Senha","str-desc-card":"Preencha os campos abaixo e enviaremos um email com instru\u00e7\u00f5es para recupera\u00e7\u00e3o de sua senha.","str-label-inputEmail":"Endere\u00e7o de Email <span class=\"text-danger\"><b>*<\/b><\/span>","str-help-inputEmail":"Preencha com o endere\u00e7o correspondente a conta que deseja recuperar.","str-texto-btn-enviar":"Enviar","str-texto-btn-voltar":"Voltar","str-titulo-pagina":"Projecta :: Recupera\u00e7\u00e3o de senha","str-header-card-sucesso":"Sucesso","str-desc-card-sucesso":"Foi enviado um email para <b><\/b>, nele est\u00e3o contidas instru\u00e7\u00f5es para a recupera\u00e7\u00e3o de sua senha, caso n\u00e3o o veja, verifique o lixo eletr\u00f4nico."}}